cubrifc.cp310-win_amd64.pyd
cubrif/__init__.py
cubrif/cubrif.py
cubrif-1.4.3.dist-info/METADATA
cubrif-1.4.3.dist-info/WHEEL
cubrif-1.4.3.dist-info/top_level.txt
cubrif-1.4.3.dist-info/RECORD
