Metadata-Version: 2.1
Name: cubrif
Version: 1.4.3
Summary: Build random forests using CUDA GPU.
Home-page: https://pypi.org/project/cubrif/
Author: Yanchao Liu
Author-email: yanchaoliu@wayne.edu
License: GPL3
Keywords: random forest,classification,regression,prediction
Classifier: Topic :: Scientific/Engineering :: Information Analysis
Classifier: Programming Language :: C
Classifier: Programming Language :: C++
Classifier: Programming Language :: Python :: 3
Classifier: Environment :: GPU :: NVIDIA CUDA
Classifier: Environment :: GPU :: NVIDIA CUDA :: 12
Requires-Python: >=3.5
Requires-Dist: numpy
Requires-Dist: pandas
